pystackflame/__init__.py
pystackflame/__main__.py
pystackflame/builders.py
pystackflame/constants.py
pystackflame-0.1.4.dist-info/licenses/LICENSE
pystackflame-0.1.4.dist-info/METADATA
pystackflame-0.1.4.dist-info/WHEEL
pystackflame-0.1.4.dist-info/entry_points.txt
pystackflame-0.1.4.dist-info/top_level.txt
pystackflame-0.1.4.dist-info/RECORD
